bsbt/__init__.py
bsbt/mock_data.py
bsbt/pipeline.py
bsbt/plm.py
bsbt-0.1.2.dist-info/METADATA
bsbt-0.1.2.dist-info/WHEEL
bsbt-0.1.2.dist-info/top_level.txt
bsbt-0.1.2.dist-info/RECORD
