Metadata-Version: 2.4
Name: bsbt
Version: 0.1.2
Summary: BSBT: Binding Sequence Benchmarking Tool - A Python package for benchmarking protein language models and predicting antibody-antigen binding.
Author-email: Ayush Laware <ayushlaware@gmail.com>
License: MIT
Project-URL: Homepage, https://github.com/ayushlaware/BSBT
Requires-Python: >=3.8
